Workbook

Sheet Реестр
A1: № | B1: Тип объекта | C1: Адрес | D1: Округ | E1: Район | F1: Метро | G1: До метро, мин | H1: Площадь, м² | I1: Участок, м² | J1: Этаж | K1: Этажность | L1: ОКН | M1: Назначение | N1: Вход | O1: Арендатор | P1: Обременения | Q1: Кадастровый № объекта | R1: Кадастровый № участка | S1: Начальная цена, ₽ | T1: Цена за м², ₽ | U1: Задаток, ₽ | V1: Шаг аукциона, ₽ | W1: Форма торгов | X1: Приём заявок с | Y1: Приём заявок до | Z1: Дней до конца приёма | AA1: Отбор участников | AB1: Дата торгов | AC1: Подведение итогов | AD1: Карточка | AE1: Процедура на ЭТП | AF1: torgi.gov.ru | AG1: Площадка | AH1: ID / № процедуры | AI1: Примечание
A2: 1 | B2: Нежилое помещение | C2: Малый Златоустинский пер., д. 8, стр. 1, этаж 1 | D2: ЦАО | E2: Басманный | F2: Китай-город | G2: 5 | H2: 42.3 | J2: 1 | K2: 3 | L2: Нет | M2: Свободное | N2: Через места общего пользования | O2: Нет | P2: Нет | Q2: 77:01:0001033:2521 | R2: — | S2: 15384000 | T2: =IF(AND(ISNUMBER(S2),ISNUMBER(H2),H2>0),S2/H2,"") -> 363687.94 | U2: 1538400 | V2: 769200 | W2: Открытый аукцион в электронной форме | X2: 46279.833 | Y2: 46335.625 | Z2: =IF(ISNUMBER(Y2),MAX(0,INT(Y2-TODAY())),"") -> 20 | AA2: 46342.417 | AB2: 46344.417 | AC2: 46344.708 | AD2: открыть ↗ | AE2: открыть ↗ | AF2: открыть ↗ | AG2: investmoscow.ru | AH2: 20198280 | AI2: Район указан по адресному справочнику (в карточке не указан).
A3: 2 | B3: Нежилое помещение | C3: Большая Никитская ул., д. 21/18, стр. 1, этаж 1 | D3: ЦАО | E3: Пресненский | F3: Арбатская | G3: 9 | H3: 13.1 | J3: 1 | K3: 2 | L3: Да | M3: Свободное | N3: Через иную собственность | O3: Нет | P3: Нет | Q3: 77:01:0001045:2432 | R3: — | S3: 17225000 | T3: =IF(AND(ISNUMBER(S3),ISNUMBER(H3),H3>0),S3/H3,"") -> 1314885.5 | U3: 1722500 | V3: 861250 | W3: Открытый аукцион в электронной форме | X3: 46289.833 | Y3: 46337.625 | Z3: =IF(ISNUMBER(Y3),MAX(0,INT(Y3-TODAY())),"") -> 22 | AA3: 46344.417 | AB3: 46346.417 | AC3: 46346.708 | AD3: открыть ↗ | AE3: открыть ↗ | AF3: открыть ↗ | AG3: investmoscow.ru | AH3: 20202772 | AI3: Объект культурного наследия.
A4: 3 | B4: Нежилое помещение | C4: ул. Бахрушина, д. 1, стр. 1, этаж 1, помещение 5/1 | D4: ЦАО | E4: Замоскворечье | F4: Павелецкая | G4: 9 | H4: 167.1 | J4: 1 | K4: 6 | L4: Нет | M4: Свободное | N4: Через подъезд | O4: Нет | P4: Нет | Q4: 77:01:0002012:3735 | R4: — | S4: 50797000 | T4: =IF(AND(ISNUMBER(S4),ISNUMBER(H4),H4>0),S4/H4,"") -> 303991.62 | U4: 5079700 | V4: 2539850 | W4: Открытый аукцион в электронной форме | X4: 46301.833 | Y4: 46335.625 | Z4: =IF(ISNUMBER(Y4),MAX(0,INT(Y4-TODAY())),"") -> 20 | AA4: 46338.417 | AB4: 46343.417 | AC4: 46343.708 | AD4: открыть ↗ | AE4: открыть ↗ | AF4: открыть ↗ | AG4: investmoscow.ru | AH4: 20208821
A5: 4 | B5: Нежилое помещение | C5: Большая Сухаревская пл., д. 1/2, стр. 1, помещ. 3/1 | D5: ЦАО | E5: Мещанский | F5: Сухаревская | G5: 2 | H5: 315.5 | J5: Подвал, 1 этаж, антресоль | K5: 3 | L5: — | M5: — | N5: — | O5: — | P5: — | Q5: — | R5: — | S5: 112951260 | T5: =IF(AND(ISNUMBER(S5),ISNUMBER(H5),H5>0),S5/H5,"") -> 358007.16 | U5: 11295126 | V5: — | W5: Аукцион на повышение (коммерческая процедура) | X5: 46308.583 | Y5: 46369.583 | Z5: =IF(ISNUMBER(Y5),MAX(0,INT(Y5-TODAY())),"") -> 54 | AA5: 46372.625 | AB5: 46373.458 | AC5: — | AD5: открыть ↗ | AE5: открыть ↗ | AG5: roseltorg.ru (com) | AH5: COM13102600087 | AI5: Продавец и организатор — АКБ «Абсолют Банк» (ПАО). Задаток — обеспечение заявки 10%. Шаг аукциона на странице не указан (он в аукционной документации). Цена с НДС 22%. Первая линия Садового кольца, 20 м от выхода метро.
A6: 5 | B6: Здание + земельный участок | C6: Каширское ш., д. 88/26, стр. 2 | D6: ЮАО | E6: Орехово-Борисово Северное | F6: Домодедовская | G6: 12 | H6: 898.3 | I6: 808 | J6: — | K6: 1 | L6: Нет | M6: Свободное | N6: — | O6: Нет | P6: Нет | Q6: 77:05:0011002:1086 | R6: 77:05:0011002:93 | S6: 158898000 | T6: =IF(AND(ISNUMBER(S6),ISNUMBER(H6),H6>0),S6/H6,"") -> 176887.45 | U6: 31779600 | V6: 1588980 | W6: Открытый аукцион в электронной форме | X6: 46302.833 | Y6: 46335.625 | Z6: =IF(ISNUMBER(Y6),MAX(0,INT(Y6-TODAY())),"") -> 20 | AA6: 46338.417 | AB6: 46343.417 | AC6: 46343.708 | AD6: открыть ↗ | AE6: открыть ↗ | AF6: открыть ↗ | AG6: investmoscow.ru | AH6: 20208859 | AI6: Цена за м² считается по площади здания.
A7: 6 | B7: Здание + земельный участок | C7: Неглинная ул., д. 18/1, стр. 2 | D7: ЦАО | E7: Мещанский | F7: Трубная | G7: 4 | H7: 634.4 | I7: 396 | J7: — | K7: 1 | L7: Нет | M7: Свободное | N7: — | O7: Нет | P7: Нет | Q7: 77:01:0001080:1014 | R7: 77:01:0001080:2978 | S7: 195014000 | T7: =IF(AND(ISNUMBER(S7),ISNUMBER(H7),H7>0),S7/H7,"") -> 307399.12 | U7: 39002800 | V7: 1950140 | W7: Открытый аукцион в электронной форме | X7: 46302.833 | Y7: 46335.625 | Z7: =IF(ISNUMBER(Y7),MAX(0,INT(Y7-TODAY())),"") -> 20 | AA7: 46338.417 | AB7: 46343.417 | AC7: 46343.708 | AD7: открыть ↗ | AE7: открыть ↗ | AF7: открыть ↗ | AG7: investmoscow.ru | AH7: 20209390 | AI7: Цена за м² считается по площади здания.
A8: 7 | B8: Нежилое помещение | C8: ул. Покровка, д. 19, этаж 1 | D8: ЦАО | E8: Басманный | F8: Чистые пруды | G8: 9 | H8: 431.2 | J8: 1 | L8: Да | M8: Свободное | N8: Через подъезд, отдельный | O8: Нет | P8: Нет | Q8: 77:01:0001029:4191 | R8: — | S8: 239527000 | T8: =IF(AND(ISNUMBER(S8),ISNUMBER(H8),H8>0),S8/H8,"") -> 555489.33 | U8: 47905400 | V8: 2395270 | W8: Открытый аукцион в электронной форме | X8: 46308.833 | Y8: 46342.625 | Z8: =IF(ISNUMBER(Y8),MAX(0,INT(Y8-TODAY())),"") -> 27 | AA8: 46345.417 | AB8: 46350.417 | AC8: 46350.708 | AD8: открыть ↗ | AE8: открыть ↗ | AF8: открыть ↗ | AG8: investmoscow.ru | AH8: 20212872 | AI8: Объект культурного наследия.
A9: 8 | B9: Здание | C9: Пятницкая ул., д. 15 | D9: ЦАО | E9: Замоскворечье | F9: Новокузнецкая | G9: 2 | H9: 1030.1 | J9: — | K9: 3 | L9: Да | M9: Свободное | N9: — | O9: Нет | P9: Нет | Q9: 77:01:0002018:1071 | R9: — | S9: 263000000 | T9: =IF(AND(ISNUMBER(S9),ISNUMBER(H9),H9>0),S9/H9,"") -> 255315.02 | U9: 131500000 | V9: 2630000 | W9: Открытый аукцион в электронной форме | X9: 46282.833 | Y9: 46339.625 | Z9: =IF(ISNUMBER(Y9),MAX(0,INT(Y9-TODAY())),"") -> 24 | AA9: 46344.417 | AB9: 46346.417 | AC9: 46346.708 | AD9: открыть ↗ | AE9: открыть ↗ | AG9: investmoscow.ru | AH9: 20182722 | AI9: В вашем списке ссылка была дважды. Вид цены — «плата за право заключения договора купли-продажи». Процедура по 178-ФЗ, ссылки на torgi.gov.ru в карточке нет. Объект культурного наследия.
A10: 9 | B10: Здание + земельный участок | C10: Краснопрудная ул., д. 3Б (земельный участок 3/5/1), здание Ярославского ПЖДП | D10: ЦАО | E10: Красносельский | F10: Красносельская | G10: 4 | H10: 1259.3 | I10: 621 | J10: — | K10: 3 | L10: — | M10: Услуги связи (ВРИ участка 3.2.3) | N10: — | O10: — | P10: По выписке ЕГРН | Q10: 77:01:0003036:1085 | R10: 77:01:0003036:4449 | S10: 289558721 | T10: =IF(AND(ISNUMBER(S10),ISNUMBER(H10),H10>0),S10/H10,"") -> 229936.25 | U10: 57911744 | V10: 5791174.4 | W10: Электронный аукцион на повышение (178-ФЗ) | X10: 46311.833 | Y10: 46351.999 | Z10: =IF(ISNUMBER(Y10),MAX(0,INT(Y10-TODAY())),"") -> 36 | AA10: 46353.999 | AB10: 46356.458 | AC10: — | AD10: открыть ↗ | AE10: открыть ↗ | AF10: открыть ↗ | AG10: roseltorg.ru | AH10: 21000003370000000430 | AI10: Продавец — АО «Почта России», организатор — АО ИФК «Солид». Продаётся единым лотом: здание 1 259,3 м² и участок 621 ± 9 м² (общая площадь 1 880,3 м²). Задаток 20%. Цена, задаток и шаг указаны в извещении torgi.gov.ru (данные взяты с зеркала torgi-ru.com, лот 8152317).

Sheet Обзор
B2: ОБЪЕКТОВ | F2: СУММА НАЧАЛЬНЫХ ЦЕН | J2: ОБЩАЯ ПЛОЩАДЬ | N2: СРЕДНЯЯ ЦЕНА ЗА М² | R2: БЛИЖАЙШИЕ ТОРГИ
B3: =COUNTA(Реестр!$C$2:$C$10) -> 9 | F3: =SUM(Реестр!$S$2:$S$10)/1000000 -> 1342.355 | J3: =SUM(Реестр!$H$2:$H$10) -> 4791.3 | N3: =SUM(Реестр!$S$2:$S$10)/SUM(Реестр!$H$2:$H$10) -> 280165.09 | R3: =MIN(Реестр!$AB$2:$AB$10) -> 46343.417
B4: в реестре | F4: по всем лотам | J4: без земельных участков | N4: взвешенная по площади | R4: =INDEX(_chart!$C$1:$C$9,MATCH(MIN(Реестр!$AB$2:$AB$10),_chart!$H$1:$H$9,0)) -> Бахрушина, 1

Sheet Сортировка
A1: Сортировать по | C1: Начальная цена, ₽
A2: Порядок | C2: По возрастанию
A4: Место | B4: Адрес | C4: Тип объекта | D4: Площадь, м² | E4: Начальная цена, ₽ | F4: Цена за м², ₽ | G4: Приём заявок до | H4: Дата торгов | I4: Значение показателя | J4: Метро | K4: Дней до конца приёма
A5: 1 | B5: =IFERROR(INDEX(Реестр!$A$2:$AI$10,MATCH(1,_calc!$C$1:$C$9,0),MATCH("Адрес",Реестр!$A$1:$AI$1,0)),"") -> Малый Златоустинский пер., д. 8, стр. 1, этаж 1 | C5: =IFERROR(INDEX(Реестр!$A$2:$AI$10,MATCH(1,_calc!$C$1:$C$9,0),MATCH("Тип объекта",Реестр!$A$1:$AI$1,0)),"") -> Нежилое помещение | D5: =IFERROR(INDEX(Реестр!$A$2:$AI$10,MATCH(1,_calc!$C$1:$C$9,0),MATCH("Площадь, м²",Реестр!$A$1:$AI$1,0)),"") -> 42.3 | E5: =IFERROR(INDEX(Реестр!$A$2:$AI$10,MATCH(1,_calc!$C$1:$C$9,0),MATCH("Начальная цена, ₽",Реестр!$A$1:$AI$1,0)),"") -> 15384000 | F5: =IFERROR(INDEX(Реестр!$A$2:$AI$10,MATCH(1,_calc!$C$1:$C$9,0),MATCH("Цена за м², ₽",Реестр!$A$1:$AI$1,0)),"") -> 363687.94 | G5: =IFERROR(INDEX(Реестр!$A$2:$AI$10,MATCH(1,_calc!$C$1:$C$9,0),MATCH("Приём заявок до",Реестр!$A$1:$AI$1,0)),"") -> 46335.625 | H5: =IFERROR(INDEX(Реестр!$A$2:$AI$10,MATCH(1,_calc!$C$1:$C$9,0),MATCH("Дата торгов",Реестр!$A$1:$AI$1,0)),"") -> 46344.417 | I5: =IFERROR(IF(AND(OR($C$1="Приём заявок до",$C$1="Дата торгов"),ISNUMBER(INDEX(_calc!$A$1:$A$9,MATCH(1,_calc!$C$1:$C$9,0)))),RIGHT("0"&DAY(INDEX(_calc!$A$1:$A$9,MATCH(1,_calc!$C$1:$C$9,0))),2)&"."&RIGHT("0"&MONTH(INDEX(_calc!$A$1:$A$9,MATCH(1,_calc!$C$1:$C$9,0))),2)&"."&YEAR(INDEX(_calc!$A$1:$A$9,MATCH(1,_calc!$C$1:$C$9,0))),INDEX(_calc!$A$1:$A$9,MATCH(1,_calc!$C$1:$C$9,0))),"") -> 15384000 | J5: =IFERROR(INDEX(Реестр!$A$2:$AI$10,MATCH(1,_calc!$C$1:$C$9,0),MATCH("Метро",Реестр!$A$1:$AI$1,0)),"") -> Китай-город | K5: =IFERROR(INDEX(Реестр!$A$2:$AI$10,MATCH(1,_calc!$C$1:$C$9,0),MATCH("Дней до конца приёма",Реестр!$A$1:$AI$1,0)),"") -> 20
A6: 2 | B6: =IFERROR(INDEX(Реестр!$A$2:$AI$10,MATCH(2,_calc!$C$1:$C$9,0),MATCH("Адрес",Реестр!$A$1:$AI$1,0)),"") -> Большая Никитская ул., д. 21/18, стр. 1, этаж 1 | C6: =IFERROR(INDEX(Реестр!$A$2:$AI$10,MATCH(2,_calc!$C$1:$C$9,0),MATCH("Тип объекта",Реестр!$A$1:$AI$1,0)),"") -> Нежилое помещение | D6: =IFERROR(INDEX(Реестр!$A$2:$AI$10,MATCH(2,_calc!$C$1:$C$9,0),MATCH("Площадь, м²",Реестр!$A$1:$AI$1,0)),"") -> 13.1 | E6: =IFERROR(INDEX(Реестр!$A$2:$AI$10,MATCH(2,_calc!$C$1:$C$9,0),MATCH("Начальная цена, ₽",Реестр!$A$1:$AI$1,0)),"") -> 17225000 | F6: =IFERROR(INDEX(Реестр!$A$2:$AI$10,MATCH(2,_calc!$C$1:$C$9,0),MATCH("Цена за м², ₽",Реестр!$A$1:$AI$1,0)),"") -> 1314885.5 | G6: =IFERROR(INDEX(Реестр!$A$2:$AI$10,MATCH(2,_calc!$C$1:$C$9,0),MATCH("Приём заявок до",Реестр!$A$1:$AI$1,0)),"") -> 46337.625 | H6: =IFERROR(INDEX(Реестр!$A$2:$AI$10,MATCH(2,_calc!$C$1:$C$9,0),MATCH("Дата торгов",Реестр!$A$1:$AI$1,0)),"") -> 46346.417 | I6: =IFERROR(IF(AND(OR($C$1="Приём заявок до",$C$1="Дата торгов"),ISNUMBER(INDEX(_calc!$A$1:$A$9,MATCH(2,_calc!$C$1:$C$9,0)))),RIGHT("0"&DAY(INDEX(_calc!$A$1:$A$9,MATCH(2,_calc!$C$1:$C$9,0))),2)&"."&RIGHT("0"&MONTH(INDEX(_calc!$A$1:$A$9,MATCH(2,_calc!$C$1:$C$9,0))),2)&"."&YEAR(INDEX(_calc!$A$1:$A$9,MATCH(2,_calc!$C$1:$C$9,0))),INDEX(_calc!$A$1:$A$9,MATCH(2,_calc!$C$1:$C$9,0))),"") -> 17225000 | J6: =IFERROR(INDEX(Реестр!$A$2:$AI$10,MATCH(2,_calc!$C$1:$C$9,0),MATCH("Метро",Реестр!$A$1:$AI$1,0)),"") -> Арбатская | K6: =IFERROR(INDEX(Реестр!$A$2:$AI$10,MATCH(2,_calc!$C$1:$C$9,0),MATCH("Дней до конца приёма",Реестр!$A$1:$AI$1,0)),"") -> 22
A7: 3 | B7: =IFERROR(INDEX(Реестр!$A$2:$AI$10,MATCH(3,_calc!$C$1:$C$9,0),MATCH("Адрес",Реестр!$A$1:$AI$1,0)),"") -> ул. Бахрушина, д. 1, стр. 1, этаж 1, помещение 5/1 | C7: =IFERROR(INDEX(Реестр!$A$2:$AI$10,MATCH(3,_calc!$C$1:$C$9,0),MATCH("Тип объекта",Реестр!$A$1:$AI$1,0)),"") -> Нежилое помещение | D7: =IFERROR(INDEX(Реестр!$A$2:$AI$10,MATCH(3,_calc!$C$1:$C$9,0),MATCH("Площадь, м²",Реестр!$A$1:$AI$1,0)),"") -> 167.1 | E7: =IFERROR(INDEX(Реестр!$A$2:$AI$10,MATCH(3,_calc!$C$1:$C$9,0),MATCH("Начальная цена, ₽",Реестр!$A$1:$AI$1,0)),"") -> 50797000 | F7: =IFERROR(INDEX(Реестр!$A$2:$AI$10,MATCH(3,_calc!$C$1:$C$9,0),MATCH("Цена за м², ₽",Реестр!$A$1:$AI$1,0)),"") -> 303991.62 | G7: =IFERROR(INDEX(Реестр!$A$2:$AI$10,MATCH(3,_calc!$C$1:$C$9,0),MATCH("Приём заявок до",Реестр!$A$1:$AI$1,0)),"") -> 46335.625 | H7: =IFERROR(INDEX(Реестр!$A$2:$AI$10,MATCH(3,_calc!$C$1:$C$9,0),MATCH("Дата торгов",Реестр!$A$1:$AI$1,0)),"") -> 46343.417 | I7: =IFERROR(IF(AND(OR($C$1="Приём заявок до",$C$1="Дата торгов"),ISNUMBER(INDEX(_calc!$A$1:$A$9,MATCH(3,_calc!$C$1:$C$9,0)))),RIGHT("0"&DAY(INDEX(_calc!$A$1:$A$9,MATCH(3,_calc!$C$1:$C$9,0))),2)&"."&RIGHT("0"&MONTH(INDEX(_calc!$A$1:$A$9,MATCH(3,_calc!$C$1:$C$9,0))),2)&"."&YEAR(INDEX(_calc!$A$1:$A$9,MATCH(3,_calc!$C$1:$C$9,0))),INDEX(_calc!$A$1:$A$9,MATCH(3,_calc!$C$1:$C$9,0))),"") -> 50797000 | J7: =IFERROR(INDEX(Реестр!$A$2:$AI$10,MATCH(3,_calc!$C$1:$C$9,0),MATCH("Метро",Реестр!$A$1:$AI$1,0)),"") -> Павелецкая | K7: =IFERROR(INDEX(Реестр!$A$2:$AI$10,MATCH(3,_calc!$C$1:$C$9,0),MATCH("Дней до конца приёма",Реестр!$A$1:$AI$1,0)),"") -> 20
A8: 4 | B8: =IFERROR(INDEX(Реестр!$A$2:$AI$10,MATCH(4,_calc!$C$1:$C$9,0),MATCH("Адрес",Реестр!$A$1:$AI$1,0)),"") -> Большая Сухаревская пл., д. 1/2, стр. 1, помещ. 3/1 | C8: =IFERROR(INDEX(Реестр!$A$2:$AI$10,MATCH(4,_calc!$C$1:$C$9,0),MATCH("Тип объекта",Реестр!$A$1:$AI$1,0)),"") -> Нежилое помещение | D8: =IFERROR(INDEX(Реестр!$A$2:$AI$10,MATCH(4,_calc!$C$1:$C$9,0),MATCH("Площадь, м²",Реестр!$A$1:$AI$1,0)),"") -> 315.5 | E8: =IFERROR(INDEX(Реестр!$A$2:$AI$10,MATCH(4,_calc!$C$1:$C$9,0),MATCH("Начальная цена, ₽",Реестр!$A$1:$AI$1,0)),"") -> 112951260 | F8: =IFERROR(INDEX(Реестр!$A$2:$AI$10,MATCH(4,_calc!$C$1:$C$9,0),MATCH("Цена за м², ₽",Реестр!$A$1:$AI$1,0)),"") -> 358007.16 | G8: =IFERROR(INDEX(Реестр!$A$2:$AI$10,MATCH(4,_calc!$C$1:$C$9,0),MATCH("Приём заявок до",Реестр!$A$1:$AI$1,0)),"") -> 46369.583 | H8: =IFERROR(INDEX(Реестр!$A$2:$AI$10,MATCH(4,_calc!$C$1:$C$9,0),MATCH("Дата торгов",Реестр!$A$1:$AI$1,0)),"") -> 46373.458 | I8: =IFERROR(IF(AND(OR($C$1="Приём заявок до",$C$1="Дата торгов"),ISNUMBER(INDEX(_calc!$A$1:$A$9,MATCH(4,_calc!$C$1:$C$9,0)))),RIGHT("0"&DAY(INDEX(_calc!$A$1:$A$9,MATCH(4,_calc!$C$1:$C$9,0))),2)&"."&RIGHT("0"&MONTH(INDEX(_calc!$A$1:$A$9,MATCH(4,_calc!$C$1:$C$9,0))),2)&"."&YEAR(INDEX(_calc!$A$1:$A$9,MATCH(4,_calc!$C$1:$C$9,0))),INDEX(_calc!$A$1:$A$9,MATCH(4,_calc!$C$1:$C$9,0))),"") -> 112951260 | J8: =IFERROR(INDEX(Реестр!$A$2:$AI$10,MATCH(4,_calc!$C$1:$C$9,0),MATCH("Метро",Реестр!$A$1:$AI$1,0)),"") -> Сухаревская | K8: =IFERROR(INDEX(Реестр!$A$2:$AI$10,MATCH(4,_calc!$C$1:$C$9,0),MATCH("Дней до конца приёма",Реестр!$A$1:$AI$1,0)),"") -> 54
A9: 5 | B9: =IFERROR(INDEX(Реестр!$A$2:$AI$10,MATCH(5,_calc!$C$1:$C$9,0),MATCH("Адрес",Реестр!$A$1:$AI$1,0)),"") -> Каширское ш., д. 88/26, стр. 2 | C9: =IFERROR(INDEX(Реестр!$A$2:$AI$10,MATCH(5,_calc!$C$1:$C$9,0),MATCH("Тип объекта",Реестр!$A$1:$AI$1,0)),"") -> Здание + земельный участок | D9: =IFERROR(INDEX(Реестр!$A$2:$AI$10,MATCH(5,_calc!$C$1:$C$9,0),MATCH("Площадь, м²",Реестр!$A$1:$AI$1,0)),"") -> 898.3 | E9: =IFERROR(INDEX(Реестр!$A$2:$AI$10,MATCH(5,_calc!$C$1:$C$9,0),MATCH("Начальная цена, ₽",Реестр!$A$1:$AI$1,0)),"") -> 158898000 | F9: =IFERROR(INDEX(Реестр!$A$2:$AI$10,MATCH(5,_calc!$C$1:$C$9,0),MATCH("Цена за м², ₽",Реестр!$A$1:$AI$1,0)),"") -> 176887.45 | G9: =IFERROR(INDEX(Реестр!$A$2:$AI$10,MATCH(5,_calc!$C$1:$C$9,0),MATCH("Приём заявок до",Реестр!$A$1:$AI$1,0)),"") -> 46335.625 | H9: =IFERROR(INDEX(Реестр!$A$2:$AI$10,MATCH(5,_calc!$C$1:$C$9,0),MATCH("Дата торгов",Реестр!$A$1:$AI$1,0)),"") -> 46343.417 | I9: =IFERROR(IF(AND(OR($C$1="Приём заявок до",$C$1="Дата торгов"),ISNUMBER(INDEX(_calc!$A$1:$A$9,MATCH(5,_calc!$C$1:$C$9,0)))),RIGHT("0"&DAY(INDEX(_calc!$A$1:$A$9,MATCH(5,_calc!$C$1:$C$9,0))),2)&"."&RIGHT("0"&MONTH(INDEX(_calc!$A$1:$A$9,MATCH(5,_calc!$C$1:$C$9,0))),2)&"."&YEAR(INDEX(_calc!$A$1:$A$9,MATCH(5,_calc!$C$1:$C$9,0))),INDEX(_calc!$A$1:$A$9,MATCH(5,_calc!$C$1:$C$9,0))),"") -> 158898000 | J9: =IFERROR(INDEX(Реестр!$A$2:$AI$10,MATCH(5,_calc!$C$1:$C$9,0),MATCH("Метро",Реестр!$A$1:$AI$1,0)),"") -> Домодедовская | K9: =IFERROR(INDEX(Реестр!$A$2:$AI$10,MATCH(5,_calc!$C$1:$C$9,0),MATCH("Дней до конца приёма",Реестр!$A$1:$AI$1,0)),"") -> 20
A10: 6 | B10: =IFERROR(INDEX(Реестр!$A$2:$AI$10,MATCH(6,_calc!$C$1:$C$9,0),MATCH("Адрес",Реестр!$A$1:$AI$1,0)),"") -> Неглинная ул., д. 18/1, стр. 2 | C10: =IFERROR(INDEX(Реестр!$A$2:$AI$10,MATCH(6,_calc!$C$1:$C$9,0),MATCH("Тип объекта",Реестр!$A$1:$AI$1,0)),"") -> Здание + земельный участок | D10: =IFERROR(INDEX(Реестр!$A$2:$AI$10,MATCH(6,_calc!$C$1:$C$9,0),MATCH("Площадь, м²",Реестр!$A$1:$AI$1,0)),"") -> 634.4 | E10: =IFERROR(INDEX(Реестр!$A$2:$AI$10,MATCH(6,_calc!$C$1:$C$9,0),MATCH("Начальная цена, ₽",Реестр!$A$1:$AI$1,0)),"") -> 195014000 | F10: =IFERROR(INDEX(Реестр!$A$2:$AI$10,MATCH(6,_calc!$C$1:$C$9,0),MATCH("Цена за м², ₽",Реестр!$A$1:$AI$1,0)),"") -> 307399.12 | G10: =IFERROR(INDEX(Реестр!$A$2:$AI$10,MATCH(6,_calc!$C$1:$C$9,0),MATCH("Приём заявок до",Реестр!$A$1:$AI$1,0)),"") -> 46335.625 | H10: =IFERROR(INDEX(Реестр!$A$2:$AI$10,MATCH(6,_calc!$C$1:$C$9,0),MATCH("Дата торгов",Реестр!$A$1:$AI$1,0)),"") -> 46343.417 | I10: =IFERROR(IF(AND(OR($C$1="Приём заявок до",$C$1="Дата торгов"),ISNUMBER(INDEX(_calc!$A$1:$A$9,MATCH(6,_calc!$C$1:$C$9,0)))),RIGHT("0"&DAY(INDEX(_calc!$A$1:$A$9,MATCH(6,_calc!$C$1:$C$9,0))),2)&"."&RIGHT("0"&MONTH(INDEX(_calc!$A$1:$A$9,MATCH(6,_calc!$C$1:$C$9,0))),2)&"."&YEAR(INDEX(_calc!$A$1:$A$9,MATCH(6,_calc!$C$1:$C$9,0))),INDEX(_calc!$A$1:$A$9,MATCH(6,_calc!$C$1:$C$9,0))),"") -> 195014000 | J10: =IFERROR(INDEX(Реестр!$A$2:$AI$10,MATCH(6,_calc!$C$1:$C$9,0),MATCH("Метро",Реестр!$A$1:$AI$1,0)),"") -> Трубная | K10: =IFERROR(INDEX(Реестр!$A$2:$AI$10,MATCH(6,_calc!$C$1:$C$9,0),MATCH("Дней до конца приёма",Реестр!$A$1:$AI$1,0)),"") -> 20
A11: 7 | B11: =IFERROR(INDEX(Реестр!$A$2:$AI$10,MATCH(7,_calc!$C$1:$C$9,0),MATCH("Адрес",Реестр!$A$1:$AI$1,0)),"") -> ул. Покровка, д. 19, этаж 1 | C11: =IFERROR(INDEX(Реестр!$A$2:$AI$10,MATCH(7,_calc!$C$1:$C$9,0),MATCH("Тип объекта",Реестр!$A$1:$AI$1,0)),"") -> Нежилое помещение | D11: =IFERROR(INDEX(Реестр!$A$2:$AI$10,MATCH(7,_calc!$C$1:$C$9,0),MATCH("Площадь, м²",Реестр!$A$1:$AI$1,0)),"") -> 431.2 | E11: =IFERROR(INDEX(Реестр!$A$2:$AI$10,MATCH(7,_calc!$C$1:$C$9,0),MATCH("Начальная цена, ₽",Реестр!$A$1:$AI$1,0)),"") -> 239527000 | F11: =IFERROR(INDEX(Реестр!$A$2:$AI$10,MATCH(7,_calc!$C$1:$C$9,0),MATCH("Цена за м², ₽",Реестр!$A$1:$AI$1,0)),"") -> 555489.33 | G11: =IFERROR(INDEX(Реестр!$A$2:$AI$10,MATCH(7,_calc!$C$1:$C$9,0),MATCH("Приём заявок до",Реестр!$A$1:$AI$1,0)),"") -> 46342.625 | H11: =IFERROR(INDEX(Реестр!$A$2:$AI$10,MATCH(7,_calc!$C$1:$C$9,0),MATCH("Дата торгов",Реестр!$A$1:$AI$1,0)),"") -> 46350.417 | I11: =IFERROR(IF(AND(OR($C$1="Приём заявок до",$C$1="Дата торгов"),ISNUMBER(INDEX(_calc!$A$1:$A$9,MATCH(7,_calc!$C$1:$C$9,0)))),RIGHT("0"&DAY(INDEX(_calc!$A$1:$A$9,MATCH(7,_calc!$C$1:$C$9,0))),2)&"."&RIGHT("0"&MONTH(INDEX(_calc!$A$1:$A$9,MATCH(7,_calc!$C$1:$C$9,0))),2)&"."&YEAR(INDEX(_calc!$A$1:$A$9,MATCH(7,_calc!$C$1:$C$9,0))),INDEX(_calc!$A$1:$A$9,MATCH(7,_calc!$C$1:$C$9,0))),"") -> 239527000 | J11: =IFERROR(INDEX(Реестр!$A$2:$AI$10,MATCH(7,_calc!$C$1:$C$9,0),MATCH("Метро",Реестр!$A$1:$AI$1,0)),"") -> Чистые пруды | K11: =IFERROR(INDEX(Реестр!$A$2:$AI$10,MATCH(7,_calc!$C$1:$C$9,0),MATCH("Дней до конца приёма",Реестр!$A$1:$AI$1,0)),"") -> 27
A12: 8 | B12: =IFERROR(INDEX(Реестр!$A$2:$AI$10,MATCH(8,_calc!$C$1:$C$9,0),MATCH("Адрес",Реестр!$A$1:$AI$1,0)),"") -> Пятницкая ул., д. 15 | C12: =IFERROR(INDEX(Реестр!$A$2:$AI$10,MATCH(8,_calc!$C$1:$C$9,0),MATCH("Тип объекта",Реестр!$A$1:$AI$1,0)),"") -> Здание | D12: =IFERROR(INDEX(Реестр!$A$2:$AI$10,MATCH(8,_calc!$C$1:$C$9,0),MATCH("Площадь, м²",Реестр!$A$1:$AI$1,0)),"") -> 1030.1 | E12: =IFERROR(INDEX(Реестр!$A$2:$AI$10,MATCH(8,_calc!$C$1:$C$9,0),MATCH("Начальная цена, ₽",Реестр!$A$1:$AI$1,0)),"") -> 263000000 | F12: =IFERROR(INDEX(Реестр!$A$2:$AI$10,MATCH(8,_calc!$C$1:$C$9,0),MATCH("Цена за м², ₽",Реестр!$A$1:$AI$1,0)),"") -> 255315.02 | G12: =IFERROR(INDEX(Реестр!$A$2:$AI$10,MATCH(8,_calc!$C$1:$C$9,0),MATCH("Приём заявок до",Реестр!$A$1:$AI$1,0)),"") -> 46339.625 | H12: =IFERROR(INDEX(Реестр!$A$2:$AI$10,MATCH(8,_calc!$C$1:$C$9,0),MATCH("Дата торгов",Реестр!$A$1:$AI$1,0)),"") -> 46346.417 | I12: =IFERROR(IF(AND(OR($C$1="Приём заявок до",$C$1="Дата торгов"),ISNUMBER(INDEX(_calc!$A$1:$A$9,MATCH(8,_calc!$C$1:$C$9,0)))),RIGHT("0"&DAY(INDEX(_calc!$A$1:$A$9,MATCH(8,_calc!$C$1:$C$9,0))),2)&"."&RIGHT("0"&MONTH(INDEX(_calc!$A$1:$A$9,MATCH(8,_calc!$C$1:$C$9,0))),2)&"."&YEAR(INDEX(_calc!$A$1:$A$9,MATCH(8,_calc!$C$1:$C$9,0))),INDEX(_calc!$A$1:$A$9,MATCH(8,_calc!$C$1:$C$9,0))),"") -> 263000000 | J12: =IFERROR(INDEX(Реестр!$A$2:$AI$10,MATCH(8,_calc!$C$1:$C$9,0),MATCH("Метро",Реестр!$A$1:$AI$1,0)),"") -> Новокузнецкая | K12: =IFERROR(INDEX(Реестр!$A$2:$AI$10,MATCH(8,_calc!$C$1:$C$9,0),MATCH("Дней до конца приёма",Реестр!$A$1:$AI$1,0)),"") -> 24
A13: 9 | B13: =IFERROR(INDEX(Реестр!$A$2:$AI$10,MATCH(9,_calc!$C$1:$C$9,0),MATCH("Адрес",Реестр!$A$1:$AI$1,0)),"") -> Краснопрудная ул., д. 3Б (земельный участок 3/5/1), здание Ярославского ПЖДП | C13: =IFERROR(INDEX(Реестр!$A$2:$AI$10,MATCH(9,_calc!$C$1:$C$9,0),MATCH("Тип объекта",Реестр!$A$1:$AI$1,0)),"") -> Здание + земельный участок | D13: =IFERROR(INDEX(Реестр!$A$2:$AI$10,MATCH(9,_calc!$C$1:$C$9,0),MATCH("Площадь, м²",Реестр!$A$1:$AI$1,0)),"") -> 1259.3 | E13: =IFERROR(INDEX(Реестр!$A$2:$AI$10,MATCH(9,_calc!$C$1:$C$9,0),MATCH("Начальная цена, ₽",Реестр!$A$1:$AI$1,0)),"") -> 289558721 | F13: =IFERROR(INDEX(Реестр!$A$2:$AI$10,MATCH(9,_calc!$C$1:$C$9,0),MATCH("Цена за м², ₽",Реестр!$A$1:$AI$1,0)),"") -> 229936.25 | G13: =IFERROR(INDEX(Реестр!$A$2:$AI$10,MATCH(9,_calc!$C$1:$C$9,0),MATCH("Приём заявок до",Реестр!$A$1:$AI$1,0)),"") -> 46351.999 | H13: =IFERROR(INDEX(Реестр!$A$2:$AI$10,MATCH(9,_calc!$C$1:$C$9,0),MATCH("Дата торгов",Реестр!$A$1:$AI$1,0)),"") -> 46356.458 | I13: =IFERROR(IF(AND(OR($C$1="Приём заявок до",$C$1="Дата торгов"),ISNUMBER(INDEX(_calc!$A$1:$A$9,MATCH(9,_calc!$C$1:$C$9,0)))),RIGHT("0"&DAY(INDEX(_calc!$A$1:$A$9,MATCH(9,_calc!$C$1:$C$9,0))),2)&"."&RIGHT("0"&MONTH(INDEX(_calc!$A$1:$A$9,MATCH(9,_calc!$C$1:$C$9,0))),2)&"."&YEAR(INDEX(_calc!$A$1:$A$9,MATCH(9,_calc!$C$1:$C$9,0))),INDEX(_calc!$A$1:$A$9,MATCH(9,_calc!$C$1:$C$9,0))),"") -> 289558721 | J13: =IFERROR(INDEX(Реестр!$A$2:$AI$10,MATCH(9,_calc!$C$1:$C$9,0),MATCH("Метро",Реестр!$A$1:$AI$1,0)),"") -> Красносельская | K13: =IFERROR(INDEX(Реестр!$A$2:$AI$10,MATCH(9,_calc!$C$1:$C$9,0),MATCH("Дней до конца приёма",Реестр!$A$1:$AI$1,0)),"") -> 36

Sheet _calc
A1: =INDEX(Реестр!$A$2:$AI$10,1,MATCH(Сортировка!$C$1,Реестр!$A$1:$AI$1,0)) -> 15384000 | B1: =IF(ISNUMBER(A1),IF(Сортировка!$C$2="По убыванию",-A1,A1),1E+300) -> 15384000 | C1: =COUNTIF($B$1:$B$9,"<"&B1)+COUNTIF($B$1:B1,B1) -> 1 | D1: Начальная цена, ₽ | E1: По возрастанию
A2: =INDEX(Реестр!$A$2:$AI$10,2,MATCH(Сортировка!$C$1,Реестр!$A$1:$AI$1,0)) -> 17225000 | B2: =IF(ISNUMBER(A2),IF(Сортировка!$C$2="По убыванию",-A2,A2),1E+300) -> 17225000 | C2: =COUNTIF($B$1:$B$9,"<"&B2)+COUNTIF($B$1:B2,B2) -> 2 | D2: Цена за м², ₽ | E2: По убыванию
A3: =INDEX(Реестр!$A$2:$AI$10,3,MATCH(Сортировка!$C$1,Реестр!$A$1:$AI$1,0)) -> 50797000 | B3: =IF(ISNUMBER(A3),IF(Сортировка!$C$2="По убыванию",-A3,A3),1E+300) -> 50797000 | C3: =COUNTIF($B$1:$B$9,"<"&B3)+COUNTIF($B$1:B3,B3) -> 3 | D3: Площадь, м²
A4: =INDEX(Реестр!$A$2:$AI$10,4,MATCH(Сортировка!$C$1,Реестр!$A$1:$AI$1,0)) -> 112951260 | B4: =IF(ISNUMBER(A4),IF(Сортировка!$C$2="По убыванию",-A4,A4),1E+300) -> 112951260 | C4: =COUNTIF($B$1:$B$9,"<"&B4)+COUNTIF($B$1:B4,B4) -> 4 | D4: Задаток, ₽
A5: =INDEX(Реестр!$A$2:$AI$10,5,MATCH(Сортировка!$C$1,Реестр!$A$1:$AI$1,0)) -> 158898000 | B5: =IF(ISNUMBER(A5),IF(Сортировка!$C$2="По убыванию",-A5,A5),1E+300) -> 158898000 | C5: =COUNTIF($B$1:$B$9,"<"&B5)+COUNTIF($B$1:B5,B5) -> 5 | D5: Шаг аукциона, ₽
A6: =INDEX(Реестр!$A$2:$AI$10,6,MATCH(Сортировка!$C$1,Реестр!$A$1:$AI$1,0)) -> 195014000 | B6: =IF(ISNUMBER(A6),IF(Сортировка!$C$2="По убыванию",-A6,A6),1E+300) -> 195014000 | C6: =COUNTIF($B$1:$B$9,"<"&B6)+COUNTIF($B$1:B6,B6) -> 6 | D6: Приём заявок до
A7: =INDEX(Реестр!$A$2:$AI$10,7,MATCH(Сортировка!$C$1,Реестр!$A$1:$AI$1,0)) -> 239527000 | B7: =IF(ISNUMBER(A7),IF(Сортировка!$C$2="По убыванию",-A7,A7),1E+300) -> 239527000 | C7: =COUNTIF($B$1:$B$9,"<"&B7)+COUNTIF($B$1:B7,B7) -> 7 | D7: Дата торгов
A8: =INDEX(Реестр!$A$2:$AI$10,8,MATCH(Сортировка!$C$1,Реестр!$A$1:$AI$1,0)) -> 263000000 | B8: =IF(ISNUMBER(A8),IF(Сортировка!$C$2="По убыванию",-A8,A8),1E+300) -> 263000000 | C8: =COUNTIF($B$1:$B$9,"<"&B8)+COUNTIF($B$1:B8,B8) -> 8 | D8: Дней до конца приёма
A9: =INDEX(Реестр!$A$2:$AI$10,9,MATCH(Сортировка!$C$1,Реестр!$A$1:$AI$1,0)) -> 289558721 | B9: =IF(ISNUMBER(A9),IF(Сортировка!$C$2="По убыванию",-A9,A9),1E+300) -> 289558721 | C9: =COUNTIF($B$1:$B$9,"<"&B9)+COUNTIF($B$1:B9,B9) -> 9 | D9: До метро, мин
D10: Участок, м²

Sheet _chart
A1: 1 | B1: =INDEX(Реестр!$AH$2:$AH$10,1) -> 20198280 | C1: =IFERROR(VLOOKUP(B1,$Y$1:$Z$9,2,0),B1) -> М. Златоустинский, 8 | D1: =INDEX(Реестр!$T$2:$T$10,1)/1000 -> 363.68794 | E1: =INDEX(Реестр!$S$2:$S$10,1)/1000000 -> 15.384 | F1: =INDEX(Реестр!$X$2:$X$10,1) -> 46279.833 | G1: =INDEX(Реестр!$Y$2:$Y$10,1) -> 46335.625 | H1: =INDEX(Реестр!$AB$2:$AB$10,1) -> 46344.417 | J1: =COUNTIF($D$1:$D$9,"<"&D1)+COUNTIF($D$1:D1,D1) -> 7 | K1: =COUNTIF($E$1:$E$9,"<"&E1)+COUNTIF($E$1:E1,E1) -> 1 | M1: =COUNTIF($H$1:$H$9,"<"&H1)+COUNTIF($H$1:H1,H1) -> 4 | P1: Цена за м², тыс. ₽ | R1: Начальная цена, млн ₽ | V1: Старт | W1: Приём заявок | X1: От конца приёма до торгов | Y1: 21000003370000000430 | Z1: Краснопрудная, 3Б
A2: 2 | B2: =INDEX(Реестр!$AH$2:$AH$10,2) -> 20202772 | C2: =IFERROR(VLOOKUP(B2,$Y$1:$Z$9,2,0),B2) -> Б. Никитская, 21/18 | D2: =INDEX(Реестр!$T$2:$T$10,2)/1000 -> 1314.8855 | E2: =INDEX(Реестр!$S$2:$S$10,2)/1000000 -> 17.225 | F2: =INDEX(Реестр!$X$2:$X$10,2) -> 46289.833 | G2: =INDEX(Реестр!$Y$2:$Y$10,2) -> 46337.625 | H2: =INDEX(Реестр!$AB$2:$AB$10,2) -> 46346.417 | J2: =COUNTIF($D$1:$D$9,"<"&D2)+COUNTIF($D$1:D2,D2) -> 9 | K2: =COUNTIF($E$1:$E$9,"<"&E2)+COUNTIF($E$1:E2,E2) -> 2 | M2: =COUNTIF($H$1:$H$9,"<"&H2)+COUNTIF($H$1:H2,H2) -> 5 | O2: =INDEX($C$1:$C$9,MATCH(1,$J$1:$J$9,0)) -> Каширское ш., 88/26 | P2: =INDEX($D$1:$D$9,MATCH(1,$J$1:$J$9,0)) -> 176.88745 | Q2: =INDEX($C$1:$C$9,MATCH(1,$K$1:$K$9,0)) -> М. Златоустинский, 8 | R2: =INDEX($E$1:$E$9,MATCH(1,$K$1:$K$9,0)) -> 15.384 | U2: =INDEX($C$1:$C$9,MATCH(9,$M$1:$M$9,0)) -> Б. Сухаревская пл., 1/2 | V2: =INDEX($F$1:$F$9,MATCH(9,$M$1:$M$9,0)) -> 46308.583 | W2: =INDEX($G$1:$G$9,MATCH(9,$M$1:$M$9,0))-V2 -> 61 | X2: =INDEX($H$1:$H$9,MATCH(9,$M$1:$M$9,0))-INDEX($G$1:$G$9,MATCH(9,$M$1:$M$9,0)) -> 3.875 | Y2: COM13102600087 | Z2: Б. Сухаревская пл., 1/2
A3: 3 | B3: =INDEX(Реестр!$AH$2:$AH$10,3) -> 20208821 | C3: =IFERROR(VLOOKUP(B3,$Y$1:$Z$9,2,0),B3) -> Бахрушина, 1 | D3: =INDEX(Реестр!$T$2:$T$10,3)/1000 -> 303.99162 | E3: =INDEX(Реестр!$S$2:$S$10,3)/1000000 -> 50.797 | F3: =INDEX(Реестр!$X$2:$X$10,3) -> 46301.833 | G3: =INDEX(Реестр!$Y$2:$Y$10,3) -> 46335.625 | H3: =INDEX(Реестр!$AB$2:$AB$10,3) -> 46343.417 | J3: =COUNTIF($D$1:$D$9,"<"&D3)+COUNTIF($D$1:D3,D3) -> 4 | K3: =COUNTIF($E$1:$E$9,"<"&E3)+COUNTIF($E$1:E3,E3) -> 3 | M3: =COUNTIF($H$1:$H$9,"<"&H3)+COUNTIF($H$1:H3,H3) -> 1 | O3: =INDEX($C$1:$C$9,MATCH(2,$J$1:$J$9,0)) -> Краснопрудная, 3Б | P3: =INDEX($D$1:$D$9,MATCH(2,$J$1:$J$9,0)) -> 229.93625 | Q3: =INDEX($C$1:$C$9,MATCH(2,$K$1:$K$9,0)) -> Б. Никитская, 21/18 | R3: =INDEX($E$1:$E$9,MATCH(2,$K$1:$K$9,0)) -> 17.225 | U3: =INDEX($C$1:$C$9,MATCH(8,$M$1:$M$9,0)) -> Краснопрудная, 3Б | V3: =INDEX($F$1:$F$9,MATCH(8,$M$1:$M$9,0)) -> 46311.833 | W3: =INDEX($G$1:$G$9,MATCH(8,$M$1:$M$9,0))-V3 -> 40.165972 | X3: =INDEX($H$1:$H$9,MATCH(8,$M$1:$M$9,0))-INDEX($G$1:$G$9,MATCH(8,$M$1:$M$9,0)) -> 4.4590278 | Y3: 20198280 | Z3: М. Златоустинский, 8
A4: 4 | B4: =INDEX(Реестр!$AH$2:$AH$10,4) -> COM13102600087 | C4: =IFERROR(VLOOKUP(B4,$Y$1:$Z$9,2,0),B4) -> Б. Сухаревская пл., 1/2 | D4: =INDEX(Реестр!$T$2:$T$10,4)/1000 -> 358.00716 | E4: =INDEX(Реестр!$S$2:$S$10,4)/1000000 -> 112.95126 | F4: =INDEX(Реестр!$X$2:$X$10,4) -> 46308.583 | G4: =INDEX(Реестр!$Y$2:$Y$10,4) -> 46369.583 | H4: =INDEX(Реестр!$AB$2:$AB$10,4) -> 46373.458 | J4: =COUNTIF($D$1:$D$9,"<"&D4)+COUNTIF($D$1:D4,D4) -> 6 | K4: =COUNTIF($E$1:$E$9,"<"&E4)+COUNTIF($E$1:E4,E4) -> 4 | M4: =COUNTIF($H$1:$H$9,"<"&H4)+COUNTIF($H$1:H4,H4) -> 9 | O4: =INDEX($C$1:$C$9,MATCH(3,$J$1:$J$9,0)) -> Пятницкая, 15 | P4: =INDEX($D$1:$D$9,MATCH(3,$J$1:$J$9,0)) -> 255.31502 | Q4: =INDEX($C$1:$C$9,MATCH(3,$K$1:$K$9,0)) -> Бахрушина, 1 | R4: =INDEX($E$1:$E$9,MATCH(3,$K$1:$K$9,0)) -> 50.797 | U4: =INDEX($C$1:$C$9,MATCH(7,$M$1:$M$9,0)) -> Покровка, 19 | V4: =INDEX($F$1:$F$9,MATCH(7,$M$1:$M$9,0)) -> 46308.833 | W4: =INDEX($G$1:$G$9,MATCH(7,$M$1:$M$9,0))-V4 -> 33.791667 | X4: =INDEX($H$1:$H$9,MATCH(7,$M$1:$M$9,0))-INDEX($G$1:$G$9,MATCH(7,$M$1:$M$9,0)) -> 7.7916667 | Y4: 20212872 | Z4: Покровка, 19
A5: 5 | B5: =INDEX(Реестр!$AH$2:$AH$10,5) -> 20208859 | C5: =IFERROR(VLOOKUP(B5,$Y$1:$Z$9,2,0),B5) -> Каширское ш., 88/26 | D5: =INDEX(Реестр!$T$2:$T$10,5)/1000 -> 176.88745 | E5: =INDEX(Реестр!$S$2:$S$10,5)/1000000 -> 158.898 | F5: =INDEX(Реестр!$X$2:$X$10,5) -> 46302.833 | G5: =INDEX(Реестр!$Y$2:$Y$10,5) -> 46335.625 | H5: =INDEX(Реестр!$AB$2:$AB$10,5) -> 46343.417 | J5: =COUNTIF($D$1:$D$9,"<"&D5)+COUNTIF($D$1:D5,D5) -> 1 | K5: =COUNTIF($E$1:$E$9,"<"&E5)+COUNTIF($E$1:E5,E5) -> 5 | M5: =COUNTIF($H$1:$H$9,"<"&H5)+COUNTIF($H$1:H5,H5) -> 2 | O5: =INDEX($C$1:$C$9,MATCH(4,$J$1:$J$9,0)) -> Бахрушина, 1 | P5: =INDEX($D$1:$D$9,MATCH(4,$J$1:$J$9,0)) -> 303.99162 | Q5: =INDEX($C$1:$C$9,MATCH(4,$K$1:$K$9,0)) -> Б. Сухаревская пл., 1/2 | R5: =INDEX($E$1:$E$9,MATCH(4,$K$1:$K$9,0)) -> 112.95126 | U5: =INDEX($C$1:$C$9,MATCH(6,$M$1:$M$9,0)) -> Пятницкая, 15 | V5: =INDEX($F$1:$F$9,MATCH(6,$M$1:$M$9,0)) -> 46282.833 | W5: =INDEX($G$1:$G$9,MATCH(6,$M$1:$M$9,0))-V5 -> 56.791667 | X5: =INDEX($H$1:$H$9,MATCH(6,$M$1:$M$9,0))-INDEX($G$1:$G$9,MATCH(6,$M$1:$M$9,0)) -> 6.7916667 | Y5: 20182722 | Z5: Пятницкая, 15
A6: 6 | B6: =INDEX(Реестр!$AH$2:$AH$10,6) -> 20209390 | C6: =IFERROR(VLOOKUP(B6,$Y$1:$Z$9,2,0),B6) -> Неглинная, 18/1 | D6: =INDEX(Реестр!$T$2:$T$10,6)/1000 -> 307.39912 | E6: =INDEX(Реестр!$S$2:$S$10,6)/1000000 -> 195.014 | F6: =INDEX(Реестр!$X$2:$X$10,6) -> 46302.833 | G6: =INDEX(Реестр!$Y$2:$Y$10,6) -> 46335.625 | H6: =INDEX(Реестр!$AB$2:$AB$10,6) -> 46343.417 | J6: =COUNTIF($D$1:$D$9,"<"&D6)+COUNTIF($D$1:D6,D6) -> 5 | K6: =COUNTIF($E$1:$E$9,"<"&E6)+COUNTIF($E$1:E6,E6) -> 6 | M6: =COUNTIF($H$1:$H$9,"<"&H6)+COUNTIF($H$1:H6,H6) -> 3 | O6: =INDEX($C$1:$C$9,MATCH(5,$J$1:$J$9,0)) -> Неглинная, 18/1 | P6: =INDEX($D$1:$D$9,MATCH(5,$J$1:$J$9,0)) -> 307.39912 | Q6: =INDEX($C$1:$C$9,MATCH(5,$K$1:$K$9,0)) -> Каширское ш., 88/26 | R6: =INDEX($E$1:$E$9,MATCH(5,$K$1:$K$9,0)) -> 158.898 | U6: =INDEX($C$1:$C$9,MATCH(5,$M$1:$M$9,0)) -> Б. Никитская, 21/18 | V6: =INDEX($F$1:$F$9,MATCH(5,$M$1:$M$9,0)) -> 46289.833 | W6: =INDEX($G$1:$G$9,MATCH(5,$M$1:$M$9,0))-V6 -> 47.791667 | X6: =INDEX($H$1:$H$9,MATCH(5,$M$1:$M$9,0))-INDEX($G$1:$G$9,MATCH(5,$M$1:$M$9,0)) -> 8.7916667 | Y6: 20202772 | Z6: Б. Никитская, 21/18
A7: 7 | B7: =INDEX(Реестр!$AH$2:$AH$10,7) -> 20212872 | C7: =IFERROR(VLOOKUP(B7,$Y$1:$Z$9,2,0),B7) -> Покровка, 19 | D7: =INDEX(Реестр!$T$2:$T$10,7)/1000 -> 555.48933 | E7: =INDEX(Реестр!$S$2:$S$10,7)/1000000 -> 239.527 | F7: =INDEX(Реестр!$X$2:$X$10,7) -> 46308.833 | G7: =INDEX(Реестр!$Y$2:$Y$10,7) -> 46342.625 | H7: =INDEX(Реестр!$AB$2:$AB$10,7) -> 46350.417 | J7: =COUNTIF($D$1:$D$9,"<"&D7)+COUNTIF($D$1:D7,D7) -> 8 | K7: =COUNTIF($E$1:$E$9,"<"&E7)+COUNTIF($E$1:E7,E7) -> 7 | M7: =COUNTIF($H$1:$H$9,"<"&H7)+COUNTIF($H$1:H7,H7) -> 7 | O7: =INDEX($C$1:$C$9,MATCH(6,$J$1:$J$9,0)) -> Б. Сухаревская пл., 1/2 | P7: =INDEX($D$1:$D$9,MATCH(6,$J$1:$J$9,0)) -> 358.00716 | Q7: =INDEX($C$1:$C$9,MATCH(6,$K$1:$K$9,0)) -> Неглинная, 18/1 | R7: =INDEX($E$1:$E$9,MATCH(6,$K$1:$K$9,0)) -> 195.014 | U7: =INDEX($C$1:$C$9,MATCH(4,$M$1:$M$9,0)) -> М. Златоустинский, 8 | V7: =INDEX($F$1:$F$9,MATCH(4,$M$1:$M$9,0)) -> 46279.833 | W7: =INDEX($G$1:$G$9,MATCH(4,$M$1:$M$9,0))-V7 -> 55.791667 | X7: =INDEX($H$1:$H$9,MATCH(4,$M$1:$M$9,0))-INDEX($G$1:$G$9,MATCH(4,$M$1:$M$9,0)) -> 8.7916667 | Y7: 20208821 | Z7: Бахрушина, 1
A8: 8 | B8: =INDEX(Реестр!$AH$2:$AH$10,8) -> 20182722 | C8: =IFERROR(VLOOKUP(B8,$Y$1:$Z$9,2,0),B8) -> Пятницкая, 15 | D8: =INDEX(Реестр!$T$2:$T$10,8)/1000 -> 255.31502 | E8: =INDEX(Реестр!$S$2:$S$10,8)/1000000 -> 263 | F8: =INDEX(Реестр!$X$2:$X$10,8) -> 46282.833 | G8: =INDEX(Реестр!$Y$2:$Y$10,8) -> 46339.625 | H8: =INDEX(Реестр!$AB$2:$AB$10,8) -> 46346.417 | J8: =COUNTIF($D$1:$D$9,"<"&D8)+COUNTIF($D$1:D8,D8) -> 3 | K8: =COUNTIF($E$1:$E$9,"<"&E8)+COUNTIF($E$1:E8,E8) -> 8 | M8: =COUNTIF($H$1:$H$9,"<"&H8)+COUNTIF($H$1:H8,H8) -> 6 | O8: =INDEX($C$1:$C$9,MATCH(7,$J$1:$J$9,0)) -> М. Златоустинский, 8 | P8: =INDEX($D$1:$D$9,MATCH(7,$J$1:$J$9,0)) -> 363.68794 | Q8: =INDEX($C$1:$C$9,MATCH(7,$K$1:$K$9,0)) -> Покровка, 19 | R8: =INDEX($E$1:$E$9,MATCH(7,$K$1:$K$9,0)) -> 239.527 | U8: =INDEX($C$1:$C$9,MATCH(3,$M$1:$M$9,0)) -> Неглинная, 18/1 | V8: =INDEX($F$1:$F$9,MATCH(3,$M$1:$M$9,0)) -> 46302.833 | W8: =INDEX($G$1:$G$9,MATCH(3,$M$1:$M$9,0))-V8 -> 32.791667 | X8: =INDEX($H$1:$H$9,MATCH(3,$M$1:$M$9,0))-INDEX($G$1:$G$9,MATCH(3,$M$1:$M$9,0)) -> 7.7916667 | Y8: 20209390 | Z8: Неглинная, 18/1
A9: 9 | B9: =INDEX(Реестр!$AH$2:$AH$10,9) -> 21000003370000000430 | C9: =IFERROR(VLOOKUP(B9,$Y$1:$Z$9,2,0),B9) -> Краснопрудная, 3Б | D9: =INDEX(Реестр!$T$2:$T$10,9)/1000 -> 229.93625 | E9: =INDEX(Реестр!$S$2:$S$10,9)/1000000 -> 289.55872 | F9: =INDEX(Реестр!$X$2:$X$10,9) -> 46311.833 | G9: =INDEX(Реестр!$Y$2:$Y$10,9) -> 46351.999 | H9: =INDEX(Реестр!$AB$2:$AB$10,9) -> 46356.458 | J9: =COUNTIF($D$1:$D$9,"<"&D9)+COUNTIF($D$1:D9,D9) -> 2 | K9: =COUNTIF($E$1:$E$9,"<"&E9)+COUNTIF($E$1:E9,E9) -> 9 | M9: =COUNTIF($H$1:$H$9,"<"&H9)+COUNTIF($H$1:H9,H9) -> 8 | O9: =INDEX($C$1:$C$9,MATCH(8,$J$1:$J$9,0)) -> Покровка, 19 | P9: =INDEX($D$1:$D$9,MATCH(8,$J$1:$J$9,0)) -> 555.48933 | Q9: =INDEX($C$1:$C$9,MATCH(8,$K$1:$K$9,0)) -> Пятницкая, 15 | R9: =INDEX($E$1:$E$9,MATCH(8,$K$1:$K$9,0)) -> 263 | U9: =INDEX($C$1:$C$9,MATCH(2,$M$1:$M$9,0)) -> Каширское ш., 88/26 | V9: =INDEX($F$1:$F$9,MATCH(2,$M$1:$M$9,0)) -> 46302.833 | W9: =INDEX($G$1:$G$9,MATCH(2,$M$1:$M$9,0))-V9 -> 32.791667 | X9: =INDEX($H$1:$H$9,MATCH(2,$M$1:$M$9,0))-INDEX($G$1:$G$9,MATCH(2,$M$1:$M$9,0)) -> 7.7916667 | Y9: 20208859 | Z9: Каширское ш., 88/26
O10: =INDEX($C$1:$C$9,MATCH(9,$J$1:$J$9,0)) -> Б. Никитская, 21/18 | P10: =INDEX($D$1:$D$9,MATCH(9,$J$1:$J$9,0)) -> 1314.8855 | Q10: =INDEX($C$1:$C$9,MATCH(9,$K$1:$K$9,0)) -> Краснопрудная, 3Б | R10: =INDEX($E$1:$E$9,MATCH(9,$K$1:$K$9,0)) -> 289.55872 | U10: =INDEX($C$1:$C$9,MATCH(1,$M$1:$M$9,0)) -> Бахрушина, 1 | V10: =INDEX($F$1:$F$9,MATCH(1,$M$1:$M$9,0)) -> 46301.833 | W10: =INDEX($G$1:$G$9,MATCH(1,$M$1:$M$9,0))-V10 -> 33.791667 | X10: =INDEX($H$1:$H$9,MATCH(1,$M$1:$M$9,0))-INDEX($G$1:$G$9,MATCH(1,$M$1:$M$9,0)) -> 7.7916667
